CHANGES
LICENSE
MANIFEST.in
README.md
setup.cfg
setup.py
test.py
runtimecheck/Timer.py
runtimecheck/__init__.py
runtimecheck.egg-info/PKG-INFO
runtimecheck.egg-info/SOURCES.txt
runtimecheck.egg-info/dependency_links.txt
runtimecheck.egg-info/not-zip-safe
runtimecheck.egg-info/top_level.txt