Metadata-Version: 2.1
Name: runtimecheck
Version: 0.0.1
Summary: check the running time of a given functions
Home-page: https://github.com/jusce17/runtimecheck
Author: Eden
Author-email: eden.juscelino@gmail.com
Maintainer: jusce17
Maintainer-email: eden.juscelino@gmail.com
License: MIT
Platform: any
Classifier: Intended Audience :: Developers
Classifier: License :: OSI Approved :: MIT License
Classifier: Operating System :: OS Independent
Classifier: Programming Language :: Python
Classifier: Programming Language :: Python :: 3
Classifier: Programming Language :: Python :: 3 :: Only
Classifier: Programming Language :: Python :: 3.6
Classifier: Programming Language :: Python :: 3.7
Classifier: Programming Language :: Python :: 3.8
Classifier: Programming Language :: Python :: 3.9
Classifier: Programming Language :: Python :: Implementation :: PyPy
Classifier: Topic :: Software Development :: Libraries :: Python Modules
Requires-Python: >=3
